<?xml version="1.0" encoding="utf-8" ?>

<ThoughtDefs>
  <!-- Thoughts food -->
  <ThoughtDef>
    <defName>AteCandy</defName>
    <durationDays>0.25</durationDays>
    <stackLimit>5</stackLimit>
    <stages>
      <li>
        <label>ate candy</label>
        <description>I ate a really tasty candy. Now i'm sugar buzzed.</description>
        <baseMoodEffect>6</baseMoodEffect>
      </li>
    </stages>
  </ThoughtDef>

  <ThoughtDef>
    <defName>HadCoffee</defName>
    <durationDays>0.25</durationDays>
    <stackLimit>5</stackLimit>
    <stages>
      <li>
        <label>Had cup of coffee</label>
        <description>Whoa, that's some strong coffee!</description>
        <baseMoodEffect>5</baseMoodEffect>
      </li>
    </stages>
  </ThoughtDef>

  <ThoughtDef>
    <defName>HadTea</defName>
    <durationDays>0.25</durationDays>
    <stackLimit>5</stackLimit>
    <stages>
      <li>
        <label>Had cup of tea</label>
        <description>I love tea!</description>
        <baseMoodEffect>5</baseMoodEffect>
      </li>
    </stages>
  </ThoughtDef>

  <ThoughtDef>
    <defName>Smoking</defName>
    <durationDays>0.25</durationDays>
    <stackLimit>5</stackLimit>
    <stages>
      <li>
        <label>Grabbed a smoke</label>
        <description>I feel calm, cool, and collected.</description>
        <baseMoodEffect>3</baseMoodEffect>
      </li>
    </stages>
  </ThoughtDef>



  <!-- Thoughts caveworldflora -->
  <ThoughtDef>
    <defName>AteRawShimmershroom</defName>
    <durationDays>1</durationDays>
    <stackLimit>1</stackLimit>
    <stages>
      <li>
        <label>ate raw shimmershroom</label>
        <description>I ate a delicious shimmershroom. It tastes so good!</description>
        <baseMoodEffect>5</baseMoodEffect>
      </li>
    </stages>
  </ThoughtDef>

  <ThoughtDef>
    <defName>BreathedGleamcapSmoke</defName>
    <durationDays>0.5</durationDays>
    <stackLimit>1</stackLimit>
    <stages>
      <li>
        <label>breathed gleamcap smoke</label>
        <description>I breathed a strange smoke from this gleamcap. I am feeling so gooood!</description>
        <baseMoodEffect>8</baseMoodEffect>
      </li>
    </stages>
  </ThoughtDef>




  <!-- Thoughts medical drink -->
  <ThoughtDef>
    <defName>HadMedicalDrink</defName>
    <durationDays>1</durationDays>
    <stackLimit>5</stackLimit>
    <stages>
      <li>
        <label>Feeling better</label>
        <description>Wow, I feel much better!</description>
        <baseMoodEffect>10</baseMoodEffect>
      </li>
    </stages>
  </ThoughtDef>











  <!-- Thoughts EPOE -->
  <ThoughtDef>
    <defName>DruggedRibThought</defName>
    <workerClass>ThoughtWorker_Hediff</workerClass>
    <hediff>DruggedRib</hediff>
    <nullifyingTraits>
      <li>Prosthophobe</li>
    </nullifyingTraits>
    <stages>
      <li>
        <label>Drugged rib</label>
        <description>I don't know why, but somehow I feel relaxed.</description>
        <baseMoodEffect>10</baseMoodEffect>
      </li>
    </stages>
  </ThoughtDef>

  <ThoughtDef>
    <defName>SilentJawThought</defName>
    <workerClass>ThoughtWorker_Hediff</workerClass>
    <hediff>SilentJaw</hediff>
    <stages>
      <li>
        <label>Silent jaw</label>
        <description>I just want to talk, it's so horrible!</description>
        <baseMoodEffect>-15</baseMoodEffect>
      </li>
    </stages>
  </ThoughtDef>

</ThoughtDefs>